ncc/__init__.py
ncc/ncc.py
netconf_console-2.3.3.dist-info/AUTHORS
netconf_console-2.3.3.dist-info/LICENSE.txt
netconf_console-2.3.3.dist-info/METADATA
netconf_console-2.3.3.dist-info/WHEEL
netconf_console-2.3.3.dist-info/entry_points.txt
netconf_console-2.3.3.dist-info/pbr.json
netconf_console-2.3.3.dist-info/top_level.txt
netconf_console-2.3.3.dist-info/RECORD
